unardiverysimplemodule/__init__.py
unardiverysimplemodule/__main__.py
unardiverysimplemodule/add.py
unardiverysimplemodule/subtract.py
unardiverysimplemodule/extras/__init__.py
unardiverysimplemodule/extras/divide.py
unardiverysimplemodule/extras/multiply.py
unardiverysimplemodule-0.0.5.dist-info/METADATA
unardiverysimplemodule-0.0.5.dist-info/WHEEL
unardiverysimplemodule-0.0.5.dist-info/top_level.txt
unardiverysimplemodule-0.0.5.dist-info/RECORD
